anguria/__init__.py
anguria/anguria.py
anguria-0.1.3.dist-info/LICENCE
anguria-0.1.3.dist-info/METADATA
anguria-0.1.3.dist-info/WHEEL
anguria-0.1.3.dist-info/top_level.txt
anguria-0.1.3.dist-info/RECORD
